{
    "type": "object",
    "properties": {
        "subscriptionId": {
            "required": true,
            "type": "string"
        },
        "resourceGroupName": {
            "required": true,
            "type": "string"
        },
        "appCollection": {
            "required": true,
            "type": "string"
        },
        "appName": {
            "required": true,
            "type": "string"
        },
        "kind": {
            "required": true,
            "type": "string",
            "enum": [
                "announcements",
                "polls",
                "dataPushes",
                "nativePushes"
            ]
        },
        "api_version": {
            "required": true,
            "type": "string"
        },
        "_skip": {
            "required": false,
            "type": "integer"
        },
        "_top": {
            "required": false,
            "type": "integer"
        },
        "_filter": {
            "required": false,
            "type": "string"
        },
        "_orderby": {
            "required": false,
            "type": "string"
        },
        "_search": {
            "required": false,
            "type": "string"
        }
    }
}